.gitignore
.gitlab-ci.yml
LICENSE
Makefile
README.rst
ct
example.cfg
setup.py
calltest/__init__.py
calltest/command.py
calltest/default.py
calltest/model.py
calltest/server.py
calltest/util.py
calltest.egg-info/PKG-INFO
calltest.egg-info/SOURCES.txt
calltest.egg-info/dependency_links.txt
calltest.egg-info/entry_points.txt
calltest.egg-info/requires.txt
calltest.egg-info/top_level.txt
calltest.egg-info/zip-safe
calltest/mode/__init__.py
calltest/mode/answer.py
calltest/mode/audio.py
calltest/mode/call.py
calltest/mode/dtmf.py
calltest/mode/play.py
calltest/mode/record.py
calltest/mode/ring.py
calltest/mode/wait.py
debian/.gitignore
debian/calltest.docs
debian/calltest.examples
debian/calltest.postinst
debian/calltest.service
debian/changelog
debian/compat
debian/control
debian/rules
debian/watch
debian/source/format