Metadata-Version: 1.2
Name: calltest
Version: 0.7.4
Summary: A distributed phone call test program
Home-page: https://github.com/smurfix/calltest
Author: Matthias Urlichs
Author-email: matthias@urlichs.de
License: proprietary
Keywords: async,asterisk
Platform: UNKNOWN
Classifier: Development Status :: 4 - Beta
Classifier: Intended Audience :: Information Technology
Classifier: Framework :: AsyncIO
Classifier: Framework :: Trio
Classifier: Operating System :: POSIX :: Linux
Classifier: Operating System :: MacOS :: MacOS X
Classifier: Operating System :: Microsoft :: Windows
Classifier: Programming Language :: Python :: 3.7
Classifier: Programming Language :: Python :: 3.8
Classifier: Programming Language :: Python :: Implementation :: CPython
Classifier: Topic :: Communications :: Telephony
Classifier: Topic :: Software Development :: Testing
Classifier: License :: OSI Approved :: GNU General Public License v3 (GPLv3)
Requires-Python: >=3.7
